cloudproxy/__init__.py
cloudproxy/__main__.py
cloudproxy/check.py
cloudproxy/main.py
cloudproxy/providers/__init__.py
cloudproxy/providers/config.py
cloudproxy/providers/manager.py
cloudproxy/providers/rolling.py
cloudproxy/providers/settings.py
cloudproxy/providers/user_data.sh
cloudproxy/providers/aws/functions.py
cloudproxy/providers/aws/main.py
cloudproxy/providers/digitalocean/__init__.py
cloudproxy/providers/digitalocean/functions.py
cloudproxy/providers/digitalocean/main.py
cloudproxy/providers/gcp/functions.py
cloudproxy/providers/gcp/main.py
cloudproxy/providers/hetzner/functions.py
cloudproxy/providers/hetzner/main.py
cloudproxy/providers/scaleway/functions.py
cloudproxy/providers/vultr/__init__.py
cloudproxy/providers/vultr/functions.py
cloudproxy/providers/vultr/main.py
cloudproxy-0.6.44.dist-info/licenses/LICENSE
examples/direct_proxy_access.py
examples/package_usage.py
cloudproxy-0.6.44.dist-info/METADATA
cloudproxy-0.6.44.dist-info/WHEEL
cloudproxy-0.6.44.dist-info/entry_points.txt
cloudproxy-0.6.44.dist-info/top_level.txt
cloudproxy-0.6.44.dist-info/RECORD
