Metadata-Version: 2.4
Name: cloudproxy
Version: 0.6.44
Summary: A tool to manage cloud-based proxies for scraping
Author-email: Christian Laffin <christian.laffin@gmail.com>
License: MIT License
Project-URL: Homepage, https://github.com/claffin/cloudproxy
Project-URL: Bug Tracker, https://github.com/claffin/cloudproxy/issues
Classifier: Programming Language :: Python :: 3
Classifier: License :: OSI Approved :: MIT License
Classifier: Operating System :: OS Independent
Classifier: Topic :: Internet :: Proxy Servers
Classifier: Topic :: System :: Networking
Requires-Python: >=3.9
License-File: LICENSE
Requires-Dist: requests>=2.32.2
Requires-Dist: apscheduler>=3.10.4
Requires-Dist: dateparser>=1.2.0
Requires-Dist: fastapi>=0.110.0
Requires-Dist: loguru>=0.7.2
Requires-Dist: python-dotenv>=1.0.1
Requires-Dist: uvicorn>=0.27.1
Requires-Dist: uvicorn-loguru-integration>=0.3.1
Requires-Dist: python-digitalocean>=1.17.0
Requires-Dist: boto3>=1.34.69
Requires-Dist: urllib3>=2.2.2
Requires-Dist: aiofiles>=23.2.1
Requires-Dist: botocore>=1.34.69
Requires-Dist: hcloud>=2.3.0
Requires-Dist: google-api-python-client>=2.122.0
Requires-Dist: anyio>=3.7.1
Requires-Dist: starlette>=0.36.3
Provides-Extra: test
Requires-Dist: pytest>=8.0.2; extra == "test"
Requires-Dist: pytest-cov>=4.1.0; extra == "test"
Requires-Dist: pytest-mock>=3.12.0; extra == "test"
Requires-Dist: httpx>=0.27.0; extra == "test"
Dynamic: license-file
